cheat_chat/__init__.py
cheat_chat/client.py
cheat_chat/commands.py
cheat_chat/database.py
cheat_chat/server.py
cheat_chat-0.4.0.dist-info/METADATA
cheat_chat-0.4.0.dist-info/WHEEL
cheat_chat-0.4.0.dist-info/top_level.txt
cheat_chat-0.4.0.dist-info/RECORD
