Metadata-Version: 2.1
Name: cheat-chat
Version: 0.4.0
Summary: A server-client chat application with Redis and MySQL support
Home-page: https://github.com/MesudeTurkmen/cheat_chat
Author: Abdullah Zeynel & Zeren Kavaz & Kerem Durgut & Mesude Türkmen
Author-email: your_email@example.com
Classifier: Programming Language :: Python :: 3
Classifier: License :: OSI Approved :: MIT License
Classifier: Operating System :: OS Independent
Requires-Python: >=3.6
Requires-Dist: asyncio
